benchbench/__init__.py
benchbench/data/__init__.py
benchbench/data/__pycache__/__init__.cpython-312.pyc
benchbench/data/bbh/__init__.py
benchbench/data/bbh/cols.txt
benchbench/data/bbh/format.py
benchbench/data/bbh/leaderboard.tsv
benchbench/data/bbh/statistic.py
benchbench/data/bbh/vanilla.tsv
benchbench/data/bigcode/__init__.py
benchbench/data/bigcode/format.py
benchbench/data/bigcode/leaderboard.tsv
benchbench/data/bigcode/vanilla.txt
benchbench/data/dummy/__init__.py
benchbench/data/glue/__init__.py
benchbench/data/glue/leaderboard.tsv
benchbench/data/heim/__init__.py
benchbench/data/heim/aesthetics_auto.tsv
benchbench/data/heim/aesthetics_human.tsv
benchbench/data/heim/alignment_auto.tsv
benchbench/data/heim/alignment_human.tsv
benchbench/data/heim/black_out.tsv
benchbench/data/heim/nsfw.tsv
benchbench/data/heim/nudity.tsv
benchbench/data/heim/originality.tsv
benchbench/data/heim/quality_auto.tsv
benchbench/data/heim/quality_human.tsv
benchbench/data/helm/__init__.py
benchbench/data/helm/accuracy.tsv
benchbench/data/helm/bias.tsv
benchbench/data/helm/calibration.tsv
benchbench/data/helm/efficiency.tsv
benchbench/data/helm/fairness.tsv
benchbench/data/helm/robustness.tsv
benchbench/data/helm/summarization.tsv
benchbench/data/helm/toxicity.tsv
benchbench/data/helm_capability/__init__.py
benchbench/data/helm_capability/format.py
benchbench/data/helm_capability/leaderboard.tsv
benchbench/data/helm_capability/vanilla.txt
benchbench/data/helm_lite/__init__.py
benchbench/data/helm_lite/format.py
benchbench/data/helm_lite/leaderboard.tsv
benchbench/data/helm_lite/vanilla.txt
benchbench/data/imagenet/__init__.py
benchbench/data/imagenet/format.py
benchbench/data/imagenet/leaderboard.tsv
benchbench/data/imagenet/leaderboard_raw.tsv
benchbench/data/imagenet/run.sh
benchbench/data/imagenet/run_imagenet.py
benchbench/data/imagenet/vanilla.txt
benchbench/data/mmlu/__init__.py
benchbench/data/mmlu/format.py
benchbench/data/mmlu/leaderboard.tsv
benchbench-1.0.1.dist-info/licenses/LICENSE.txt
benchbench-1.0.1.dist-info/METADATA
benchbench-1.0.1.dist-info/WHEEL
benchbench-1.0.1.dist-info/top_level.txt
benchbench-1.0.1.dist-info/RECORD
