Metadata-Version: 2.4
Name: benchbench
Version: 1.0.1
Summary: Tools for measuring sensitivity and diversity of multi-task benchmarks.
Author: Guanhua Zhang
License: MIT
Classifier: Development Status :: 3 - Alpha
Classifier: License :: OSI Approved :: MIT License
Classifier: Intended Audience :: Science/Research
Classifier: Topic :: Scientific/Engineering :: Artificial Intelligence
Classifier: Natural Language :: English
Classifier: Programming Language :: Python :: 3
Classifier: Programming Language :: Python :: 3.7
Classifier: Programming Language :: Python :: 3.8
Classifier: Programming Language :: Python :: 3.9
Classifier: Programming Language :: Python :: 3.10
Classifier: Programming Language :: Python :: 3.11
Classifier: Programming Language :: Python :: 3.12
Requires-Python: >=3.7
License-File: LICENSE.txt
Requires-Dist: scipy
Requires-Dist: numpy
Requires-Dist: torch
Requires-Dist: pandas
Requires-Dist: joblib
Requires-Dist: scikit-learn
Requires-Dist: zarth_utils==1.0
Dynamic: license-file
